{
    "AX": {
        "error": 0.005361248304995334, 
        "fit": "average", 
        "value": 0.05738904027005429
    }, 
    "CDD": {
        "error": 2.7499759810489606e-06, 
        "fit": "average", 
        "value": 6.255160581350957e-06
    }, 
    "H1": {
        "error": 0.004098039960790092, 
        "fit": "average", 
        "value": -0.0347254606969902
    }, 
    "H2": {
        "error": 0.005429375963879126, 
        "fit": "average", 
        "value": 0.06494997864212408
    }, 
    "L1": {
        "error": 0.005193364549467507, 
        "fit": "average", 
        "value": 0.13253904249814846
    }, 
    "L2": {
        "error": 0.001939989078575836, 
        "fit": "average", 
        "value": -0.03149330165569484
    }
}