{
    "AX": {
        "error": 0.004502439845905965, 
        "fit": "average", 
        "value": 0.06532812292499113
    }, 
    "CDD": {
        "error": 3.624747194411086e-06, 
        "fit": "average", 
        "value": 1.1259289046431724e-05
    }, 
    "H1": {
        "error": 0.00436349060955019, 
        "fit": "average", 
        "value": -0.027577617895533493
    }, 
    "H2": {
        "error": 0.005353990919889884, 
        "fit": "average", 
        "value": 0.07320571315089612
    }, 
    "L1": {
        "error": 0.004941320093903538, 
        "fit": "average", 
        "value": 0.1436850732159824
    }, 
    "L2": {
        "error": 0.002025520261876576, 
        "fit": "average", 
        "value": -0.06418188291258733
    }
}