{
    "Ar36": {
        "error": 0.0003093818958163518, 
        "fit": "Parabolic", 
        "value": 0.020429210815422594
    }, 
    "Ar37": {
        "error": 0.0026166021910804, 
        "fit": "linear", 
        "value": -0.013952466025417262
    }, 
    "Ar38": {
        "error": 0.006000208116004929, 
        "fit": "linear", 
        "value": 0.2447512230030296
    }, 
    "Ar39": {
        "error": 0.010075430555217577, 
        "fit": "Parabolic", 
        "value": 8.095665848770103
    }, 
    "Ar40": {
        "error": 0.050005349532356136, 
        "fit": "Parabolic", 
        "value": 998.9638005881807
    }, 
    "Ar41": {
        "error": 0.005781111303700011, 
        "fit": "linear", 
        "value": 0.129352262618682
    }
}