{
    "AX": {
        "error": 0.005319208696219524, 
        "fit": "average", 
        "value": 0.05256584713290624
    }, 
    "CDD": {
        "error": 1.9331985725577695e-05, 
        "fit": "average", 
        "value": 0.0003152600994325052
    }, 
    "H1": {
        "error": 0.005370990103536165, 
        "fit": "average", 
        "value": 0.025990027800471806
    }, 
    "H2": {
        "error": 0.005682462618007638, 
        "fit": "average", 
        "value": 0.06395228362006128
    }, 
    "L1": {
        "error": 0.003929797308259223, 
        "fit": "average", 
        "value": 0.13693598918721664
    }, 
    "L2": {
        "error": 0.0020985471304348384, 
        "fit": "average", 
        "value": 0.0002864729991285777
    }
}