{
    "AX": {
        "error": 0.005162623248526336,
        "error_type": "SEM",
        "filter_outliers_dict": {
            "filter_outliers": true,
            "iterations": 1,
            "std_devs": 3,
            "use_iqr_filtering": false,
            "use_standard_deviation_filtering": false
        },
        "fit": "average",
        "fn": 119,
        "include_baseline_error": false,
        "n": 120,
        "outlier_excluded": [
            96
        ],
        "reviewed": true,
        "user_excluded": [],
        "value": 0.049032397251263134
    },
    "CDD": {
        "error": 1.3277374184730303e-05,
        "error_type": "SEM",
        "filter_outliers_dict": {
            "filter_outliers": true,
            "iterations": 1,
            "std_devs": 10,
            "use_iqr_filtering": false,
            "use_standard_deviation_filtering": false
        },
        "fit": "average",
        "fn": 120,
        "include_baseline_error": false,
        "n": 120,
        "outlier_excluded": [],
        "reviewed": true,
        "user_excluded": [],
        "value": 0.00014261766470250828
    },
    "H1": {
        "error": 0.0040994799517387655,
        "error_type": "SEM",
        "filter_outliers_dict": {
            "filter_outliers": true,
            "iterations": 1,
            "std_devs": 3,
            "use_iqr_filtering": false,
            "use_standard_deviation_filtering": false
        },
        "fit": "average",
        "fn": 119,
        "include_baseline_error": false,
        "n": 120,
        "outlier_excluded": [
            103
        ],
        "reviewed": true,
        "user_excluded": [],
        "value": 0.002399514793680527
    },
    "H2": {
        "error": 0.005587534349207591,
        "error_type": "SEM",
        "filter_outliers_dict": {
            "filter_outliers": true,
            "iterations": 1,
            "std_devs": 3,
            "use_iqr_filtering": false,
            "use_standard_deviation_filtering": false
        },
        "fit": "average",
        "fn": 120,
        "include_baseline_error": false,
        "n": 120,
        "outlier_excluded": [],
        "reviewed": true,
        "user_excluded": [],
        "value": 0.08081125049842133
    },
    "L1": {
        "error": 0.004747165633275932,
        "error_type": "SEM",
        "filter_outliers_dict": {
            "filter_outliers": true,
            "iterations": 1,
            "std_devs": 3,
            "use_iqr_filtering": false,
            "use_standard_deviation_filtering": false
        },
        "fit": "average",
        "fn": 118,
        "include_baseline_error": false,
        "n": 120,
        "outlier_excluded": [
            66,
            23
        ],
        "reviewed": true,
        "user_excluded": [],
        "value": 0.13511183241508523
    },
    "L2": {
        "error": 0.00203773964100622,
        "fit": "average",
        "value": -7.824359378334837e-05
    }
}