{
    "Ar36": {
        "error": 0.00023500256485434198, 
        "fit": "Parabolic", 
        "value": 0.00810698322289582
    }, 
    "Ar37": {
        "error": 0.0023823322441720546, 
        "fit": "linear", 
        "value": 0.06902274509447193
    }, 
    "Ar38": {
        "error": 0.005985082172747319, 
        "fit": "linear", 
        "value": 0.38963625705959193
    }, 
    "Ar39": {
        "error": 0.01184236899990877, 
        "fit": "Parabolic", 
        "value": 19.43037776834811
    }, 
    "Ar40": {
        "error": 0.08405928400353711, 
        "fit": "Parabolic", 
        "value": 2354.8053458514855
    }, 
    "Ar41": {
        "error": 0.005955578990858741, 
        "fit": "linear", 
        "value": 0.15118553506093446
    }
}